gherila/__init__.py
gherila/brave.py
gherila/exceptions.py
gherila/http.py
gherila/instagram.py
gherila/models.py
gherila/tiktok.py
gherila-1.0.4.dist-info/licenses/LICENSE
gherila-1.0.4.dist-info/METADATA
gherila-1.0.4.dist-info/WHEEL
gherila-1.0.4.dist-info/top_level.txt
gherila-1.0.4.dist-info/RECORD
