Metadata-Version: 2.4
Name: gherila
Version: 1.0.4
Summary: An async package destioned to fetch information from different platforms
Home-page: https://github.com/br4nch/gherila
Author: s4nica
License: MIT License
Project-URL: Issues, https://github.com/br4nch/gherila/issues
Classifier: Programming Language :: Python :: 3.8
Classifier: Programming Language :: Python :: 3.9
Classifier: Programming Language :: Python :: 3.10
Classifier: Programming Language :: Python :: 3.11
Classifier: Programming Language :: Python :: 3.12
Classifier: Programming Language :: Python :: 3.13
Classifier: License :: OSI Approved :: MIT License
Classifier: Operating System :: OS Independent
Requires-Python: >=3.8.0
License-File: LICENSE
Requires-Dist: munch
Requires-Dist: aiohttp
Requires-Dist: pydantic
Requires-Dist: orjson
Dynamic: home-page
Dynamic: license-file
Dynamic: requires-dist
Dynamic: requires-python
